dissect_site/__init__.py
dissect_site/__main__.py
dissect_site/dissect_site.py
dissect_site/tests/__init__.py
dissect_site/tests/test_dissect_site.py
dissect_site-0.0.3.2.dist-info/METADATA
dissect_site-0.0.3.2.dist-info/WHEEL
dissect_site-0.0.3.2.dist-info/entry_points.txt
dissect_site-0.0.3.2.dist-info/top_level.txt
dissect_site-0.0.3.2.dist-info/RECORD
