Metadata-Version: 2.1
Name: dissect-site
Version: 0.0.3.2
Summary: Get the title and heading of the site
Author: Cuong Doan
Author-email: <cuong.doan@asnet.com.vn>
License: UNKNOWN
Keywords: python,dissect_site
Platform: UNKNOWN
Classifier: Development Status :: 3 - Alpha
Classifier: Intended Audience :: Education
Classifier: Programming Language :: Python :: 3
Classifier: Operating System :: MacOS :: MacOS X
Classifier: Operating System :: Microsoft :: Windows
Classifier: Operating System :: POSIX :: Linux
Requires-Dist: argparse
Requires-Dist: validators
Requires-Dist: requests
Requires-Dist: beautifulsoup4
